<?xml version="1.0" encoding="UTF-8"?><record_update table="sp_instance">
    <sp_instance action="INSERT_OR_UPDATE">
        <active>true</active>
        <class_name/>
        <color>default</color>
        <css/>
        <glyph/>
        <id/>
        <order>1</order>
        <roles/>
        <short_description/>
        <size>md</size>
        <sp_column display_value="1">7176ad404f612300f006121f9310c7d0</sp_column>
        <sp_widget display_value="UTASSP My Open Tickets Widget">426e70624fd12300f006121f9310c756</sp_widget>
        <sys_class_name>sp_instance</sys_class_name>
        <sys_created_by>admin</sys_created_by>
        <sys_created_on>2018-10-29 15:41:29</sys_created_on>
        <sys_customer_update>false</sys_customer_update>
        <sys_id>244769804f612300f006121f9310c75b</sys_id>
        <sys_mod_count>1</sys_mod_count>
        <sys_name>My Open Tickets</sys_name>
        <sys_package display_value="utassp" source="x_287765_utassp">2e58c8624f112300f006121f9310c726</sys_package>
        <sys_policy/>
        <sys_replace_on_upgrade>false</sys_replace_on_upgrade>
        <sys_scope display_value="utassp">2e58c8624f112300f006121f9310c726</sys_scope>
        <sys_update_name>sp_instance_244769804f612300f006121f9310c75b</sys_update_name>
        <sys_updated_by>admin</sys_updated_by>
        <sys_updated_on>2018-10-29 15:42:55</sys_updated_on>
        <title>My Open Tickets</title>
        <url/>
        <widget_parameters><![CDATA[{
	"portal": {
		"value": "",
		"displayValue": ""
	},
	"max_number_of_elements_shown_on_the_list": {
		"value": null,
		"displayValue": ""
	},
	"ishidden": {
		"value": "true",
		"displayValue": "true"
	},
	"pageid": {
		"value": "utassp01_index",
		"displayValue": "index"
	}
}]]></widget_parameters>
    </sp_instance>
</record_update>
